rancoord.py
rancoord-0.0.6.dist-info/LICENSE
rancoord-0.0.6.dist-info/METADATA
rancoord-0.0.6.dist-info/WHEEL
rancoord-0.0.6.dist-info/top_level.txt
rancoord-0.0.6.dist-info/RECORD
