Metadata-Version: 2.1
Name: rancoord
Version: 0.0.6
Summary: RanCoord is a Python package for random sampling of geographic coordinates.
Home-page: https://github.com/hugodscarvalho/rancoord
Author: Hugo Carvalho
Author-email: hugodanielsilvacarvalho.hc@gmail.com
License: UNKNOWN
Keywords: coordinates,random,generation,sampling,python,geographic coordinates,geocoder,distance-matrix
Platform: UNKNOWN
Classifier: Programming Language :: Python :: 3
Classifier: License :: OSI Approved :: MIT License
Classifier: Operating System :: OS Independent
License-File: LICENSE
Requires-Dist: Shapely (>=1.8.1)
Requires-Dist: geopy (>=2.2.0)
Requires-Dist: XlsxWriter (>=3.0.3)
Requires-Dist: requests (>=2.27.1)
Requires-Dist: numpy (>=1.22.3)
Requires-Dist: folium (>=0.12.1)
